_meshiki.cpython-310-x86_64-linux-gnu.so
meshiki/__init__.py
meshiki-0.0.7.dist-info/METADATA
meshiki-0.0.7.dist-info/WHEEL
meshiki-0.0.7.dist-info/top_level.txt
meshiki-0.0.7.dist-info/RECORD
meshiki-0.0.7.dist-info/licenses/LICENSE
