Metadata-Version: 2.4
Name: meshiki
Version: 0.0.7
Summary: Unusual mesh processing tools
Home-page: https://github.com/ashawkey/meshiki
Author: kiui
Classifier: Programming Language :: Python :: 3
License-File: LICENSE
Requires-Dist: numpy
Requires-Dist: pybind11
Requires-Dist: trimesh
Requires-Dist: kiui
Requires-Dist: pymeshlab
Dynamic: author
Dynamic: classifier
Dynamic: description
Dynamic: description-content-type
Dynamic: home-page
Dynamic: license-file
Dynamic: requires-dist
Dynamic: summary
